HPRheoPlot/HPRheoPlot.py
HPRheoPlot/__init__.py
HPRheoPlot/__main__.py
HPRheoPlot-1.0.4.dist-info/METADATA
HPRheoPlot-1.0.4.dist-info/WHEEL
HPRheoPlot-1.0.4.dist-info/entry_points.txt
HPRheoPlot-1.0.4.dist-info/top_level.txt
HPRheoPlot-1.0.4.dist-info/RECORD
